{
    "time": {
        "cpu_time_user": "00:00:00.800",
        "cpu_time_system": "00:00:00.070",
        "runtime": "00:00:00.906",
        "cpu_time_iowait": "00:00:00.000"
    },
    "peak_resources": {
        "cpu_percent": 108.9,
        "memory_rss": "128MiB",
        "memory_vms": "276MiB",
        "threads": 2
    },
    "avg_resources": {
        "cpu_percent": 78.53636363636363,
        "memory_rss": "75MiB",
        "memory_vms": "185MiB",
        "threads": 1.5454545454545454
    }
}